cocoviz/__init__.py
cocoviz/_typing.py
cocoviz/_version.py
cocoviz/exceptions.py
cocoviz/indicator.py
cocoviz/result.py
cocoviz/rtp.py
cocoviz/targets.py
cocoviz/utilities.py
coco_visualize-0.2.0rc1.dist-info/METADATA
coco_visualize-0.2.0rc1.dist-info/WHEEL
coco_visualize-0.2.0rc1.dist-info/licenses/AUTHORS
coco_visualize-0.2.0rc1.dist-info/licenses/LICENSE
coco_visualize-0.2.0rc1.dist-info/RECORD
