Metadata-Version: 2.4
Name: coco-visualize
Version: 0.2.0rc1
Summary: Standalone COCO visualization toolbox
Project-URL: Homepage, https://coco-platform.org/
Project-URL: Issues, https://github.com/numbbo/coco-visualize/issues
Author-email: Dimo Brockhoff <dimo.brockhoff@inria.fr>, Nikolaus Hansen <nikolaus.hansen@inria.fr>, Olaf Mersmann <olafm@p-value.net>, Tea Tušar <tea.tusar@ijs.si>
License: BSD-3-Clause
License-File: AUTHORS
License-File: LICENSE
Classifier: Development Status :: 4 - Beta
Classifier: License :: OSI Approved :: BSD License
Classifier: Programming Language :: Python
Classifier: Programming Language :: Python :: 3.10
Classifier: Programming Language :: Python :: 3.11
Classifier: Programming Language :: Python :: 3.12
Classifier: Programming Language :: Python :: 3.13
Classifier: Programming Language :: Python :: Implementation :: CPython
Requires-Python: >=3.10
Requires-Dist: matplotlib>=3.7
Requires-Dist: numpy>=2.0
Requires-Dist: polars>=0.20
Requires-Dist: scipy>=1.14.0
Provides-Extra: parquet
Requires-Dist: pyarrow>=22.0.0; extra == 'parquet'
